{
  "response": {
    "code": 200,
    "data": {
      "shop": {
        "tsId": "fakeString",
        "url": "fakeString",
        "name": "fakeString",
        "languageISO2": "fakeString",
        "targetMarketISO3": "fakeString",
        "trustMark": {
          "status": "fakeString",
          "validFrom": "fakeString",
          "validTo": "fakeString"
        }
      }
    },
    "message": "SUCCESS",
    "responseInfo": {
      "apiVersion": "2.4.15"
    },
    "status": "SUCCESS"
  }
}